docstra/__init__.py
docstra/api/__init__.py
docstra/api/app.py
docstra/api/dependencies.py
docstra/api/endpoints/__init__.py
docstra/api/endpoints/chat.py
docstra/api/endpoints/ingest.py
docstra/api/endpoints/init.py
docstra/api/endpoints/query.py
docstra/api/endpoints/sessions.py
docstra/api/endpoints/status.py
docstra/api/models.py
docstra/cli/__init__.py
docstra/cli/__main__.py
docstra/cli/base.py
docstra/cli/commands/__init__.py
docstra/cli/commands/base.py
docstra/cli/commands/chat.py
docstra/cli/commands/docs.py
docstra/cli/commands/ingest.py
docstra/cli/commands/init.py
docstra/cli/commands/query.py
docstra/cli/commands/serve.py
docstra/cli/commands/sessions.py
docstra/cli/main.py
docstra/cli/ui.py
docstra/core/__init__.py
docstra/core/base.py
docstra/core/config.py
docstra/core/container.py
docstra/core/context.py
docstra/core/database.py
docstra/core/errors.py
docstra/core/factory.py
docstra/core/file_watcher.py
docstra/core/indexer.py
docstra/core/interfaces.py
docstra/core/llm.py
docstra/core/loader.py
docstra/core/logger.py
docstra/core/model_provider.py
docstra/core/retriever.py
docstra/core/service.py
docstra/core/services.py
docstra/core/session.py
docstra/core/vectorstore.py
docstra-0.1.14.dist-info/METADATA
docstra-0.1.14.dist-info/WHEEL
docstra-0.1.14.dist-info/entry_points.txt
docstra-0.1.14.dist-info/RECORD
