Metadata-Version: 2.3
Name: docstra
Version: 0.1.14
Summary: An LLM-powered CLI tool and Python package for generating repository-level documentation from code.
Author: Jørgen Andresen Osberg
Author-email: jorgen.osberg@gmail.com>, Jonathan Selstad Hofstein <
Requires-Python: >=3.12,<4.0
Classifier: Programming Language :: Python :: 3
Classifier: Programming Language :: Python :: 3.12
Classifier: Programming Language :: Python :: 3.13
Requires-Dist: chromadb (>=0.5.12,<0.6.0)
Requires-Dist: click (>=8.1.8,<9.0.0)
Requires-Dist: fastapi (>=0.115.4,<0.116.0)
Requires-Dist: langchain (>=0.3.3,<0.4.0)
Requires-Dist: langchain-anthropic (>=0.3.8,<0.4.0)
Requires-Dist: langchain-chroma (>=0.1.4,<0.2.0)
Requires-Dist: langchain-community (>=0.3.2,<0.4.0)
Requires-Dist: langchain-openai (>=0.2.2,<0.3.0)
Requires-Dist: langchain-text-splitters (>=0.3.2,<0.4.0)
Requires-Dist: openai (>=1.51.2,<2.0.0)
Requires-Dist: packaging (>=24.0,<25.0)
Requires-Dist: pathspec (>=0.12.1,<0.13.0)
Requires-Dist: python-dotenv (>=1.0.1,<2.0.0)
Requires-Dist: redis (>=5.2.1,<6.0.0)
Requires-Dist: requests (>=2.31.0,<3.0.0)
Requires-Dist: rich (>=13.9.4,<14.0.0)
Requires-Dist: tree-sitter (>=0.23.2,<0.24.0)
Requires-Dist: tree-sitter-html (>=0.23.2,<0.24.0)
Requires-Dist: tree-sitter-javascript (>=0.23.1,<0.24.0)
Requires-Dist: tree-sitter-json (>=0.24.8,<0.25.0)
Requires-Dist: tree-sitter-markdown (>=0.3.2,<0.4.0)
Requires-Dist: tree-sitter-python (>=0.23.4,<0.24.0)
Requires-Dist: tree-sitter-typescript (>=0.23.2,<0.24.0)
Requires-Dist: uvicorn (>=0.32.0,<0.33.0)
Requires-Dist: watchdog (>=6.0.0,<7.0.0)
Requires-Dist: websockets (>=14.2,<15.0)
